chocs/__init__.py
chocs/__version__.py
chocs/application.py
chocs/errors.py
chocs/http/__init__.py
chocs/http/http_body.py
chocs/http/http_cookies.py
chocs/http/http_error.py
chocs/http/http_headers.py
chocs/http/http_message.py
chocs/http/http_method.py
chocs/http/http_multipart_message_parser.py
chocs/http/http_parsed_body.py
chocs/http/http_query_string.py
chocs/http/http_request.py
chocs/http/http_response.py
chocs/http/http_status.py
chocs/middleware/__init__.py
chocs/middleware/application_middleware.py
chocs/middleware/middleware.py
chocs/query/__init__.py
chocs/query/expression.py
chocs/query/query_criteria.py
chocs/query/sorting.py
chocs/routing.py
chocs/serverless/__init__.py
chocs/serverless/aws.py
chocs/serverless/serverless.py
chocs/serverless/wrapper.py
chocs/testing.py
chocs/types.py
chocs/wsgi/__init__.py
chocs/wsgi/bjoern_support.py
chocs/wsgi/cherrypy_support.py
chocs/wsgi/gunicorn_support.py
chocs/wsgi/wsgi_support.py
chocs-1.6.1.dist-info/LICENSE
chocs-1.6.1.dist-info/WHEEL
chocs-1.6.1.dist-info/METADATA
chocs-1.6.1.dist-info/RECORD
