Metadata-Version: 2.1
Name: chocs
Version: 1.6.1
Summary: Lightweight and powerful WSGI/AWS lambda framework for rapid building rest applications.
Home-page: https://github.com/kodemore/chocs
License: MIT
Keywords: http,serverless,aws,framework,router,request,response,cookies,routing,rest,wsgi
Author: Dawid Kraczkowski
Author-email: dawid.kraczkowski@gmail.com
Requires-Python: >=3.8,<4.0
Classifier: Development Status :: 5 - Production/Stable
Classifier: Intended Audience :: Developers
Classifier: License :: OSI Approved :: MIT License
Classifier: Natural Language :: English
Classifier: Programming Language :: Python
Classifier: Programming Language :: Python :: 3
Classifier: Programming Language :: Python :: 3.10
Classifier: Programming Language :: Python :: 3.8
Classifier: Programming Language :: Python :: 3.9
Classifier: Topic :: Internet :: WWW/HTTP :: WSGI :: Application
Classifier: Topic :: Internet :: WWW/HTTP :: WSGI :: Middleware
Classifier: Topic :: Software Development :: Libraries
Classifier: Topic :: Software Development :: Libraries :: Python Modules
Requires-Dist: pyyaml (>=5.3.1,<7.0.0)
Project-URL: Documentation, https://github.com/kodemore/chocs
Project-URL: Repository, https://github.com/kodemore/chocs
